[
  {
    "Name": "Cerasuolo d'Abruzzo",
    "Company": "Cantina Tollo",
    "Style": "Rosé",
    "ABV": 12,
    "Calories": 110,
    "oz": 5,
    "Origin": "Italy",
    "Rating": 0,
    "Favorites": false
  },
  {
    "Name": "Controguerra",
    "Company": "Tenuta Torri Cantine",
    "Style": "Red",
    "ABV": 13,
    "Calories": 120,
    "oz": 5,
    "Origin": "Italy",
    "Rating": 0,
    "Favorites": false
  },
  {
    "Name": "Montepulciano d'Abruzzo",
    "Company": "Cantina Zaccagnini",
    "Style": "Red",
    "ABV": 14,
    "Calories": 125,
    "oz": 5,
    "Origin": "Italy",
    "Rating": 0,
    "Favorites": false
  },
  {
    "Name": "Terre Tollesi",
    "Company": "Cantina Tollo",
    "Style": "Red",
    "ABV": 13,
    "Calories": 120,
    "oz": 5,
    "Origin": "Italy",
    "Rating": 0,
    "Favorites": false
  },
  {
    "Name": "Trebbiano d'Abruzzo DOC",
    "Company": "Cantina Frentana",
    "Style": "White",
    "ABV": 12,
    "Calories": 110,
    "oz": 5,
    "Origin": "Italy",
    "Rating": 0,
    "Favorites": false
  },
  {
    "Name": "Villamagna",
    "Company": "Villamagna DOC",
    "Style": "Red",
    "ABV": 13,
    "Calories": 120,
    "oz": 5,
    "Origin": "Italy",
    "Rating": 0,
    "Favorites": false
  },
  {
    "Name": "Aglianico del Vulture",
    "Company": "Cantine del Notaio",
    "Style": "Red",
    "ABV": 13,
    "Calories": 120,
    "oz": 5,
    "Origin": "Italy",
    "Rating": 0,
    "Favorites": false
  },
  {
    "Name": "Matera",
    "Company": "Cantina di Matera",
    "Style": "Red",
    "ABV": 14,
    "Calories": 125,
    "oz": 5,
    "Origin": "Italy",
    "Rating": 0,
    "Favorites": false
  },
  {
    "Name": "Terre dell'Alta Val d'Agri",
    "Company": "Cantina Terre dell'Alta Val d'Agri",
    "Style": "Red",
    "ABV": 13,
    "Calories": 120,
    "oz": 5,
    "Origin": "Italy",
    "Rating": 0,
    "Favorites": false
  },
  {
    "Name": "Bivongi",
    "Company": "Cantina Sociale di Bivongi",
    "Style": "Red",
    "ABV": 13,
    "Calories": 120,
    "oz": 5,
    "Origin": "Italy",
    "Rating": 0,
    "Favorites": false
  },
  {
    "Name": "Cirò",
    "Company": "Librandi",
    "Style": "Red",
    "ABV": 12,
    "Calories": 115,
    "oz": 5,
    "Origin": "Italy",
    "Rating": 0,
    "Favorites": false
  },
  {
    "Name": "Donnici",
    "Company": "Cantina Statti",
    "Style": "Red",
    "ABV": 13,
    "Calories": 120,
    "oz": 5,
    "Origin": "Italy",
    "Rating": 0,
    "Favorites": false
  },
  {
    "Name": "Greco di Bianco",
    "Company": "Ferrara",
    "Style": "White",
    "ABV": 13,
    "Calories": 110,
    "oz": 5,
    "Origin": "Italy",
    "Rating": 0,
    "Favorites": false
  },
  {
    "Name": "Lamezia",
    "Company": "Cantine Viola",
    "Style": "Red",
    "ABV": 13,
    "Calories": 120,
    "oz": 5,
    "Origin": "Italy",
    "Rating": 0,
    "Favorites": false
  },
  {
    "Name": "Melissa",
    "Company": "Azienda Agricola Duca Sanfelice",
    "Style": "Red",
    "ABV": 13,
    "Calories": 120,
    "oz": 5,
    "Origin": "Italy",
    "Rating": 0,
    "Favorites": false
  },
  {
    "Name": "Pollino",
    "Company": "Cantina San Francesco",
    "Style": "Red",
    "ABV": 12,
    "Calories": 115,
    "oz": 5,
    "Origin": "Italy",
    "Rating": 0,
    "Favorites": false
  },
  {
    "Name": "Sant'Anna di Isola Capo Rizzuto",
    "Company": "Azienda Agricola Giovanni Bosco",
    "Style": "Red",
    "ABV": 13,
    "Calories": 120,
    "oz": 5,
    "Origin": "Italy",
    "Rating": 0,
    "Favorites": false
  },
  {
    "Name": "San Vito di Luzzi",
    "Company": "Cantina Colacino",
    "Style": "Red",
    "ABV": 12,
    "Calories": 115,
    "oz": 5,
    "Origin": "Italy",
    "Rating": 0,
    "Favorites": false
  },
  {
    "Name": "Savuto",
    "Company": "Azienda Agricola Librandi",
    "Style": "Red",
    "ABV": 13,
    "Calories": 120,
    "oz": 5,
    "Origin": "Italy",
    "Rating": 0,
    "Favorites": false
  },
  {
    "Name": "Scavigna",
    "Company": "Cantina Statti",
    "Style": "Red",
    "ABV": 13,
    "Calories": 120,
    "oz": 5,
    "Origin": "Italy",
    "Rating": 0,
    "Favorites": false
  },
  {
    "Name": "Verbicaro",
    "Company": "Cantina Statti",
    "Style": "Red",
    "ABV": 12,
    "Calories": 115,
    "oz": 5,
    "Origin": "Italy",
    "Rating": 0,
    "Favorites": false
  },
  {
    "Name": "Aversa Asprinio",
    "Company": "Cantina Sociale di Aversa",
    "Style": "White",
    "ABV": 12,
    "Calories": 110,
    "oz": 5,
    "Origin": "Italy",
    "Rating": 0,
    "Favorites": false
  },
  {
    "Name": "Campi Flegrei",
    "Company": "Cantine Astroni",
    "Style": "Red",
    "ABV": 13,
    "Calories": 120,
    "oz": 5,
    "Origin": "Italy",
    "Rating": 0,
    "Favorites": false
  },
  {
    "Name": "Capri",
    "Company": "Tenuta San Michele",
    "Style": "White",
    "ABV": 12,
    "Calories": 110,
    "oz": 5,
    "Origin": "Italy",
    "Rating": 0,
    "Favorites": false
  },
  {
    "Name": "Castel San Lorenzo",
    "Company": "Cantina Castel San Lorenzo",
    "Style": "Red",
    "ABV": 13,
    "Calories": 120,
    "oz": 5,
    "Origin": "Italy",
    "Rating": 0,
    "Favorites": false
  },
  {
    "Name": "Cilento",
    "Company": "Cantine del Notaio",
    "Style": "Red",
    "ABV": 14,
    "Calories": 125,
    "oz": 5,
    "Origin": "Italy",
    "Rating": 0,
    "Favorites": false
  },
  {
    "Name": "Costa d'Amalfi",
    "Company": "Marisa Cuomo",
    "Style": "White",
    "ABV": 12,
    "Calories": 110,
    "oz": 5,
    "Origin": "Italy",
    "Rating": 0,
    "Favorites": false
  },
  {
    "Name": "Falerno del Massico",
    "Company": "Villa Matilde",
    "Style": "Red",
    "ABV": 13,
    "Calories": 120,
    "oz": 5,
    "Origin": "Italy",
    "Rating": 0,
    "Favorites": false
  },
  {
    "Name": "Falanghina del Sannio",
    "Company": "Terre Stregate",
    "Style": "White",
    "ABV": 12,
    "Calories": 110,
    "oz": 5,
    "Origin": "Italy",
    "Rating": 0,
    "Favorites": false
  },
  {
    "Name": "Galluccio",
    "Company": "Cantina del Gallo",
    "Style": "Red",
    "ABV": 13,
    "Calories": 120,
    "oz": 5,
    "Origin": "Italy",
    "Rating": 0,
    "Favorites": false
  },
  {
    "Name": "Guardiolo",
    "Company": "Azienda Agricola Guardiolo",
    "Style": "Red",
    "ABV": 12,
    "Calories": 115,
    "oz": 5,
    "Origin": "Italy",
    "Rating": 0,
    "Favorites": false
  },
  {
    "Name": "Irpinia",
    "Company": "Feudi di San Gregorio",
    "Style": "Red",
    "ABV": 13,
    "Calories": 120,
    "oz": 5,
    "Origin": "Italy",
    "Rating": 0,
    "Favorites": false
  },
  {
    "Name": "Ischia",
    "Company": "Cantina Ischia",
    "Style": "White",
    "ABV": 12,
    "Calories": 110,
    "oz": 5,
    "Origin": "Italy",
    "Rating": 0,
    "Favorites": false
  },
  {
    "Name": "Penisola Sorrentina",
    "Company": "Cantina del Vesuvio",
    "Style": "Red",
    "ABV": 13,
    "Calories": 120,
    "oz": 5,
    "Origin": "Italy",
    "Rating": 0,
    "Favorites": false
  },
  {
    "Name": "Sannio",
    "Company": "La Guardiense",
    "Style": "Red",
    "ABV": 12,
    "Calories": 115,
    "oz": 5,
    "Origin": "Italy",
    "Rating": 0,
    "Favorites": false
  },
  {
    "Name": "Sant'Agata dei Goti",
    "Company": "Mastroberardino",
    "Style": "Red",
    "ABV": 13,
    "Calories": 120,
    "oz": 5,
    "Origin": "Italy",
    "Rating": 0,
    "Favorites": false
  },
  {
    "Name": "Solopaca",
    "Company": "Cantina del Taburno",
    "Style": "Red",
    "ABV": 13,
    "Calories": 120,
    "oz": 5,
    "Origin": "Italy",
    "Rating": 0,
    "Favorites": false
  },
  {
    "Name": "Taburno",
    "Company": "Cantina del Taburno",
    "Style": "Red",
    "ABV": 13,
    "Calories": 120,
    "oz": 5,
    "Origin": "Italy",
    "Rating": 0,
    "Favorites": false
  },
  {
    "Name": "Vesuvio",
    "Company": "Cantina del Vesuvio",
    "Style": "Red",
    "ABV": 13,
    "Calories": 120,
    "oz": 5,
    "Origin": "Italy",
    "Rating": 0,
    "Favorites": false
  },
  {
    "Name": "Bosco Eliceo",
    "Company": "Cantina Bosco Eliceo",
    "Style": "Red",
    "ABV": 12,
    "Calories": 120,
    "oz": 5,
    "Origin": "Italy",
    "Rating": 0,
    "Favorites": false
  },
  {
    "Name": "Cagnina di Romagna",
    "Company": "Cantine Lini",
    "Style": "Red",
    "ABV": 13,
    "Calories": 125,
    "oz": 5,
    "Origin": "Italy",
    "Rating": 0,
    "Favorites": false
  },
  {
    "Name": "Colli Bolognesi",
    "Company": "Cantina dei Colli Bolognesi",
    "Style": "Red",
    "ABV": 13,
    "Calories": 120,
    "oz": 5,
    "Origin": "Italy",
    "Rating": 0,
    "Favorites": false
  },
  {
    "Name": "Colli Bolognesi Classico Pignoletto",
    "Company": "Cantina Pignoletto",
    "Style": "White",
    "ABV": 12,
    "Calories": 110,
    "oz": 5,
    "Origin": "Italy",
    "Rating": 0,
    "Favorites": false
  },
  {
    "Name": "Colli di Faenza",
    "Company": "Cantina Faenza",
    "Style": "Red",
    "ABV": 12,
    "Calories": 115,
    "oz": 5,
    "Origin": "Italy",
    "Rating": 0,
    "Favorites": false
  },
  {
    "Name": "Colli di Imola",
    "Company": "Cantina di Imola",
    "Style": "Red",
    "ABV": 13,
    "Calories": 120,
    "oz": 5,
    "Origin": "Italy",
    "Rating": 0,
    "Favorites": false
  },
  {
    "Name": "Colli di Parma",
    "Company": "Cantina di Parma",
    "Style": "Red",
    "ABV": 13,
    "Calories": 120,
    "oz": 5,
    "Origin": "Italy",
    "Rating": 0,
    "Favorites": false
  },
  {
    "Name": "Colli di Rimini",
    "Company": "Cantina Rimini",
    "Style": "Red",
    "ABV": 12,
    "Calories": 115,
    "oz": 5,
    "Origin": "Italy",
    "Rating": 0,
    "Favorites": false
  },
  {
    "Name": "Colli Piacentini",
    "Company": "Cantina Piacentini",
    "Style": "Red",
    "ABV": 13,
    "Calories": 120,
    "oz": 5,
    "Origin": "Italy",
    "Rating": 0,
    "Favorites": false
  },
  {
    "Name": "Colli Romagna Centrale",
    "Company": "Cantina Romagna Centrale",
    "Style": "Red",
    "ABV": 12,
    "Calories": 115,
    "oz": 5,
    "Origin": "Italy",
    "Rating": 0,
    "Favorites": false
  },
  {
    "Name": "Gutturnio",
    "Company": "Cantina Gutturnio",
    "Style": "Red",
    "ABV": 13,
    "Calories": 120,
    "oz": 5,
    "Origin": "Italy",
    "Rating": 0,
    "Favorites": false
  },
  {
    "Name": "Lambrusco di Sorbara",
    "Company": "Cantina di Sorbara",
    "Style": "Red",
    "ABV": 12,
    "Calories": 115,
    "oz": 5,
    "Origin": "Italy",
    "Rating": 0,
    "Favorites": false
  },
  {
    "Name": "Lambrusco Grasparossa di Castelvetro",
    "Company": "Cantina di Castelvetro",
    "Style": "Red",
    "ABV": 13,
    "Calories": 120,
    "oz": 5,
    "Origin": "Italy",
    "Rating": 0,
    "Favorites": false
  },
  {
    "Name": "Lambrusco Salamino di Santacroce",
    "Company": "Cantina Salamino",
    "Style": "Red",
    "ABV": 12,
    "Calories": 115,
    "oz": 5,
    "Origin": "Italy",
    "Rating": 0,
    "Favorites": false
  },
  {
    "Name": "Modena",
    "Company": "Cantina di Modena",
    "Style": "Red",
    "ABV": 13,
    "Calories": 120,
    "oz": 5,
    "Origin": "Italy",
    "Rating": 0,
    "Favorites": false
  },
  {
    "Name": "Ortrugo",
    "Company": "Cantina Ortrugo",
    "Style": "White",
    "ABV": 12,
    "Calories": 110,
    "oz": 5,
    "Origin": "Italy",
    "Rating": 0,
    "Favorites": false
  },
  {
    "Name": "Pagadebit di Romagna",
    "Company": "Cantina Pagadebit",
    "Style": "White",
    "ABV": 12,
    "Calories": 110,
    "oz": 5,
    "Origin": "Italy",
    "Rating": 0,
    "Favorites": false
  },
  {
    "Name": "Reggiano",
    "Company": "Cantina Reggiano",
    "Style": "Red",
    "ABV": 13,
    "Calories": 120,
    "oz": 5,
    "Origin": "Italy",
    "Rating": 0,
    "Favorites": false
  },
  {
    "Name": "Reno",
    "Company": "Cantina Reno",
    "Style": "Red",
    "ABV": 13,
    "Calories": 120,
    "oz": 5,
    "Origin": "Italy",
    "Rating": 0,
    "Favorites": false
  },
  {
    "Name": "Romagna Albana Spumante",
    "Company": "Cantina Romagna Albana",
    "Style": "White",
    "ABV": 12,
    "Calories": 110,
    "oz": 5,
    "Origin": "Italy",
    "Rating": 0,
    "Favorites": false
  },
  {
    "Name": "Sangiovese di Romagna",
    "Company": "Cantina Sangiovese Romagna",
    "Style": "Red",
    "ABV": 13,
    "Calories": 120,
    "oz": 5,
    "Origin": "Italy",
    "Rating": 0,
    "Favorites": false
  },
  {
    "Name": "Trebbiano di Romagna",
    "Company": "Cantina Trebbiano Romagna",
    "Style": "White",
    "ABV": 12,
    "Calories": 110,
    "oz": 5,
    "Origin": "Italy",
    "Rating": 0,
    "Favorites": false
  },
  {
    "Name": "Carso",
    "Company": "Cantina Carso",
    "Style": "Red",
    "ABV": 12,
    "Calories": 120,
    "oz": 5,
    "Origin": "Italy",
    "Rating": 0,
    "Favorites": false
  },
  {
    "Name": "Colli Orientali del Friuli",
    "Company": "Cantina Colli Orientali",
    "Style": "White",
    "ABV": 12,
    "Calories": 110,
    "oz": 5,
    "Origin": "Italy",
    "Rating": 0,
    "Favorites": false
  },
  {
    "Name": "Colli Orientali del Friuli Cialla",
    "Company": "Cantina Cialla",
    "Style": "Red",
    "ABV": 13,
    "Calories": 120,
    "oz": 5,
    "Origin": "Italy",
    "Rating": 0,
    "Favorites": false
  },
  {
    "Name": "Colli Orientali del Friuli Rosazzo",
    "Company": "Cantina Rosazzo",
    "Style": "White",
    "ABV": 12,
    "Calories": 110,
    "oz": 5,
    "Origin": "Italy",
    "Rating": 0,
    "Favorites": false
  },
  {
    "Name": "Collio Goriziano (Collio)",
    "Company": "Cantina Collio",
    "Style": "White",
    "ABV": 12,
    "Calories": 110,
    "oz": 5,
    "Origin": "Italy",
    "Rating": 0,
    "Favorites": false
  },
  {
    "Name": "delle Venezie",
    "Company": "Cantina delle Venezie",
    "Style": "Red",
    "ABV": 13,
    "Calories": 120,
    "oz": 5,
    "Origin": "Italy",
    "Rating": 0,
    "Favorites": false
  },
  {
    "Name": "Friuli Annia",
    "Company": "Cantina Friuli Annia",
    "Style": "White",
    "ABV": 12,
    "Calories": 110,
    "oz": 5,
    "Origin": "Italy",
    "Rating": 0,
    "Favorites": false
  },
  {
    "Name": "Friuli Aquileia",
    "Company": "Cantina Friuli Aquileia",
    "Style": "White",
    "ABV": 12,
    "Calories": 110,
    "oz": 5,
    "Origin": "Italy",
    "Rating": 0,
    "Favorites": false
  },
  {
    "Name": "Friuli Grave",
    "Company": "Cantina Friuli Grave",
    "Style": "Red",
    "ABV": 13,
    "Calories": 120,
    "oz": 5,
    "Origin": "Italy",
    "Rating": 0,
    "Favorites": false
  },
  {
    "Name": "Friuli Isonzo",
    "Company": "Cantina Friuli Isonzo",
    "Style": "White",
    "ABV": 12,
    "Calories": 110,
    "oz": 5,
    "Origin": "Italy",
    "Rating": 0,
    "Favorites": false
  },
  {
    "Name": "Friuli Latisana",
    "Company": "Cantina Friuli Latisana",
    "Style": "Red",
    "ABV": 13,
    "Calories": 120,
    "oz": 5,
    "Origin": "Italy",
    "Rating": 0,
    "Favorites": false
  },
  {
    "Name": "Lison Pramaggiore",
    "Company": "Cantina Lison Pramaggiore",
    "Style": "Red",
    "ABV": 13,
    "Calories": 120,
    "oz": 5,
    "Origin": "Italy",
    "Rating": 0,
    "Favorites": false
  },
  {
    "Name": "Aleatico di Gradoli",
    "Company": "Cantina Aleatico di Gradoli",
    "Style": "Red",
    "ABV": 13,
    "Calories": 120,
    "oz": 5,
    "Origin": "Italy",
    "Rating": 0,
    "Favorites": false
  },
  {
    "Name": "Aprilia",
    "Company": "Cantina Aprilia",
    "Style": "Red",
    "ABV": 12,
    "Calories": 115,
    "oz": 5,
    "Origin": "Italy",
    "Rating": 0,
    "Favorites": false
  },
  {
    "Name": "Atina",
    "Company": "Cantina Atina",
    "Style": "Red",
    "ABV": 13,
    "Calories": 120,
    "oz": 5,
    "Origin": "Italy",
    "Rating": 0,
    "Favorites": false
  },
  {
    "Name": "Bianco Capena",
    "Company": "Cantina Bianco Capena",
    "Style": "White",
    "ABV": 12,
    "Calories": 110,
    "oz": 5,
    "Origin": "Italy",
    "Rating": 0,
    "Favorites": false
  },
  {
    "Name": "Castelli Romani",
    "Company": "Cantina Castelli Romani",
    "Style": "Red",
    "ABV": 13,
    "Calories": 120,
    "oz": 5,
    "Origin": "Italy",
    "Rating": 0,
    "Favorites": false
  },
  {
    "Name": "Cerveteri",
    "Company": "Cantina Cerveteri",
    "Style": "Red",
    "ABV": 13,
    "Calories": 120,
    "oz": 5,
    "Origin": "Italy",
    "Rating": 0,
    "Favorites": false
  },
  {
    "Name": "Cesanese del Piglio",
    "Company": "Cantina Cesanese del Piglio",
    "Style": "Red",
    "ABV": 13,
    "Calories": 120,
    "oz": 5,
    "Origin": "Italy",
    "Rating": 0,
    "Favorites": false
  },
  {
    "Name": "Cesanese di Affile",
    "Company": "Cantina Cesanese di Affile",
    "Style": "Red",
    "ABV": 13,
    "Calories": 120,
    "oz": 5,
    "Origin": "Italy",
    "Rating": 0,
    "Favorites": false
  },
  {
    "Name": "Cesanese di Olevano Romano",
    "Company": "Cantina Cesanese di Olevano Romano",
    "Style": "Red",
    "ABV": 13,
    "Calories": 120,
    "oz": 5,
    "Origin": "Italy",
    "Rating": 0,
    "Favorites": false
  },
  {
    "Name": "Circeo",
    "Company": "Cantina Circeo",
    "Style": "Red",
    "ABV": 12,
    "Calories": 115,
    "oz": 5,
    "Origin": "Italy",
    "Rating": 0,
    "Favorites": false
  },
  {
    "Name": "Colli Albani",
    "Company": "Cantina Colli Albani",
    "Style": "White",
    "ABV": 12,
    "Calories": 110,
    "oz": 5,
    "Origin": "Italy",
    "Rating": 0,
    "Favorites": false
  },
  {
    "Name": "Colli della Sabina",
    "Company": "Cantina Colli della Sabina",
    "Style": "Red",
    "ABV": 13,
    "Calories": 120,
    "oz": 5,
    "Origin": "Italy",
    "Rating": 0,
    "Favorites": false
  },
  {
    "Name": "Colli Etruschi Viterbesi",
    "Company": "Cantina Colli Etruschi Viterbesi",
    "Style": "Red",
    "ABV": 13,
    "Calories": 120,
    "oz": 5,
    "Origin": "Italy",
    "Rating": 0,
    "Favorites": false
  },
  {
    "Name": "Colli Lanuvini",
    "Company": "Cantina Colli Lanuvini",
    "Style": "Red",
    "ABV": 13,
    "Calories": 120,
    "oz": 5,
    "Origin": "Italy",
    "Rating": 0,
    "Favorites": false
  },
  {
    "Name": "Cori",
    "Company": "Cantina Cori",
    "Style": "Red",
    "ABV": 13,
    "Calories": 120,
    "oz": 5,
    "Origin": "Italy",
    "Rating": 0,
    "Favorites": false
  },
  {
    "Name": "Est! Est!! Est!!! di Montefiascone",
    "Company": "Cantina Montefiascone",
    "Style": "White",
    "ABV": 12,
    "Calories": 110,
    "oz": 5,
    "Origin": "Italy",
    "Rating": 0,
    "Favorites": false
  },
  {
    "Name": "Frascati",
    "Company": "Cantina Frascati",
    "Style": "White",
    "ABV": 12,
    "Calories": 110,
    "oz": 5,
    "Origin": "Italy",
    "Rating": 0,
    "Favorites": false
  },
  {
    "Name": "Genazzano",
    "Company": "Cantina Genazzano",
    "Style": "Red",
    "ABV": 13,
    "Calories": 120,
    "oz": 5,
    "Origin": "Italy",
    "Rating": 0,
    "Favorites": false
  },
  {
    "Name": "Marino",
    "Company": "Cantina Marino",
    "Style": "Red",
    "ABV": 13,
    "Calories": 120,
    "oz": 5,
    "Origin": "Italy",
    "Rating": 0,
    "Favorites": false
  },
  {
    "Name": "Montecompatri Colonna",
    "Company": "Cantina Montecompatri Colonna",
    "Style": "Red",
    "ABV": 13,
    "Calories": 120,
    "oz": 5,
    "Origin": "Italy",
    "Rating": 0,
    "Favorites": false
  },
  {
    "Name": "Nettuno",
    "Company": "Cantina Nettuno",
    "Style": "Red",
    "ABV": 13,
    "Calories": 120,
    "oz": 5,
    "Origin": "Italy",
    "Rating": 0,
    "Favorites": false
  },
  {
    "Name": "Orvieto",
    "Company": "Cantina Orvieto",
    "Style": "White",
    "ABV": 12,
    "Calories": 110,
    "oz": 5,
    "Origin": "Italy",
    "Rating": 0,
    "Favorites": false
  },
  {
    "Name": "Roma",
    "Company": "Cantina Roma",
    "Style": "Red",
    "ABV": 13,
    "Calories": 120,
    "oz": 5,
    "Origin": "Italy",
    "Rating": 0,
    "Favorites": false
  },
  {
    "Name": "Tarquinia",
    "Company": "Cantina Tarquinia",
    "Style": "Red",
    "ABV": 13,
    "Calories": 120,
    "oz": 5,
    "Origin": "Italy",
    "Rating": 0,
    "Favorites": false
  },
  {
    "Name": "Terracina",
    "Company": "Cantina Terracina",
    "Style": "White",
    "ABV": 12,
    "Calories": 110,
    "oz": 5,
    "Origin": "Italy",
    "Rating": 0,
    "Favorites": false
  },
  {
    "Name": "Velletri",
    "Company": "Cantina Velletri",
    "Style": "Red",
    "ABV": 13,
    "Calories": 120,
    "oz": 5,
    "Origin": "Italy",
    "Rating": 0,
    "Favorites": false
  },
  {
    "Name": "Cinque Terre",
    "Company": "Cantina Cinque Terre",
    "Style": "White",
    "ABV": 12,
    "Calories": 110,
    "oz": 5,
    "Origin": "Italy",
    "Rating": 0,
    "Favorites": false
  },
  {
    "Name": "Cinque Terre Sciacchetrà",
    "Company": "Cantina Cinque Terre Sciacchetrà",
    "Style": "Dessert",
    "ABV": 15,
    "Calories": 150,
    "oz": 5,
    "Origin": "Italy",
    "Rating": 0,
    "Favorites": false
  },
  {
    "Name": "Colli di Luni",
    "Company": "Cantina Colli di Luni",
    "Style": "Red",
    "ABV": 13,
    "Calories": 120,
    "oz": 5,
    "Origin": "Italy",
    "Rating": 0,
    "Favorites": false
  },
  {
    "Name": "Colline di Levanto",
    "Company": "Cantina Colline di Levanto",
    "Style": "White",
    "ABV": 12,
    "Calories": 110,
    "oz": 5,
    "Origin": "Italy",
    "Rating": 0,
    "Favorites": false
  },
  {
    "Name": "Golfo del Tigullio",
    "Company": "Cantina Golfo del Tigullio",
    "Style": "White",
    "ABV": 12,
    "Calories": 110,
    "oz": 5,
    "Origin": "Italy",
    "Rating": 0,
    "Favorites": false
  },
  {
    "Name": "Riviera Ligure di Ponente",
    "Company": "Cantina Riviera Ligure di Ponente",
    "Style": "Red",
    "ABV": 13,
    "Calories": 120,
    "oz": 5,
    "Origin": "Italy",
    "Rating": 0,
    "Favorites": false
  },
  {
    "Name": "Rossese di Dolceacqua",
    "Company": "Cantina Rossese di Dolceacqua",
    "Style": "Red",
    "ABV": 13,
    "Calories": 120,
    "oz": 5,
    "Origin": "Italy",
    "Rating": 0,
    "Favorites": false
  },
  {
    "Name": "Val Polcevera",
    "Company": "Cantina Val Polcevera",
    "Style": "Red",
    "ABV": 13,
    "Calories": 120,
    "oz": 5,
    "Origin": "Italy",
    "Rating": 0,
    "Favorites": false
  },
  {
    "Name": "Pornassio",
    "Company": "Cantina Pornassio",
    "Style": "Red",
    "ABV": 13,
    "Calories": 120,
    "oz": 5,
    "Origin": "Italy",
    "Rating": 0,
    "Favorites": false
  },
  {
    "Name": "Botticino",
    "Company": "Cantina Botticino",
    "Style": "Red",
    "ABV": 13,
    "Calories": 120,
    "oz": 5,
    "Origin": "Italy",
    "Rating": 0,
    "Favorites": false
  },
  {
    "Name": "Bonarda dell'Oltrepo Pavese",
    "Company": "Cantina Bonarda dell'Oltrepo Pavese",
    "Style": "Red",
    "ABV": 13,
    "Calories": 120,
    "oz": 5,
    "Origin": "Italy",
    "Rating": 0,
    "Favorites": false
  },
  {
    "Name": "Buttafuoco dell'Oltrepo Pavese",
    "Company": "Cantina Buttafuoco dell'Oltrepo Pavese",
    "Style": "Red",
    "ABV": 13,
    "Calories": 120,
    "oz": 5,
    "Origin": "Italy",
    "Rating": 0,
    "Favorites": false
  },
  {
    "Name": "Casteggio",
    "Company": "Cantina Casteggio",
    "Style": "Red",
    "ABV": 13,
    "Calories": 120,
    "oz": 5,
    "Origin": "Italy",
    "Rating": 0,
    "Favorites": false
  },
  {
    "Name": "Capriano del Colle",
    "Company": "Cantina Capriano del Colle",
    "Style": "Red",
    "ABV": 13,
    "Calories": 120,
    "oz": 5,
    "Origin": "Italy",
    "Rating": 0,
    "Favorites": false
  },
  {
    "Name": "Cellatica",
    "Company": "Cantina Cellatica",
    "Style": "Red",
    "ABV": 13,
    "Calories": 120,
    "oz": 5,
    "Origin": "Italy",
    "Rating": 0,
    "Favorites": false
  },
  {
    "Name": "Garda",
    "Company": "Cantina Garda",
    "Style": "White",
    "ABV": 12,
    "Calories": 110,
    "oz": 5,
    "Origin": "Italy",
    "Rating": 0,
    "Favorites": false
  },
  {
    "Name": "Garda Colli Mantovani",
    "Company": "Cantina Garda Colli Mantovani",
    "Style": "Red",
    "ABV": 13,
    "Calories": 120,
    "oz": 5,
    "Origin": "Italy",
    "Rating": 0,
    "Favorites": false
  },
  {
    "Name": "Lambrusco Mantovano",
    "Company": "Cantina Lambrusco Mantovano",
    "Style": "Red",
    "ABV": 13,
    "Calories": 120,
    "oz": 5,
    "Origin": "Italy",
    "Rating": 0,
    "Favorites": false
  },
  {
    "Name": "Lugana",
    "Company": "Cantina Lugana",
    "Style": "White",
    "ABV": 12,
    "Calories": 110,
    "oz": 5,
    "Origin": "Italy",
    "Rating": 0,
    "Favorites": false
  },
  {
    "Name": "Oltrepò Pavese",
    "Company": "Cantina Oltrepò Pavese",
    "Style": "Red",
    "ABV": 13,
    "Calories": 120,
    "oz": 5,
    "Origin": "Italy",
    "Rating": 0,
    "Favorites": false
  },
  {
    "Name": "Riviera del Garda Bresciano",
    "Company": "Cantina Riviera del Garda Bresciano",
    "Style": "White",
    "ABV": 12,
    "Calories": 110,
    "oz": 5,
    "Origin": "Italy",
    "Rating": 0,
    "Favorites": false
  },
  {
    "Name": "San Colombano al Lambro",
    "Company": "Cantina San Colombano al Lambro",
    "Style": "Red",
    "ABV": 13,
    "Calories": 120,
    "oz": 5,
    "Origin": "Italy",
    "Rating": 0,
    "Favorites": false
  },
  {
    "Name": "San Martino della Battaglia",
    "Company": "Cantina San Martino della Battaglia",
    "Style": "Red",
    "ABV": 13,
    "Calories": 120,
    "oz": 5,
    "Origin": "Italy",
    "Rating": 0,
    "Favorites": false
  },
  {
    "Name": "Scanzo",
    "Company": "Cantina Scanzo",
    "Style": "Red",
    "ABV": 13,
    "Calories": 120,
    "oz": 5,
    "Origin": "Italy",
    "Rating": 0,
    "Favorites": false
  },
  {
    "Name": "Terre di Franciacorta",
    "Company": "Cantina Terre di Franciacorta",
    "Style": "White",
    "ABV": 12,
    "Calories": 110,
    "oz": 5,
    "Origin": "Italy",
    "Rating": 0,
    "Favorites": false
  },
  {
    "Name": "Valcalepio",
    "Company": "Cantina Valcalepio",
    "Style": "Red",
    "ABV": 13,
    "Calories": 120,
    "oz": 5,
    "Origin": "Italy",
    "Rating": 0,
    "Favorites": false
  },
  {
    "Name": "Valtellina Rosso",
    "Company": "Cantina Valtellina Rosso",
    "Style": "Red",
    "ABV": 13,
    "Calories": 120,
    "oz": 5,
    "Origin": "Italy",
    "Rating": 0,
    "Favorites": false
  },
  {
    "Name": "Valtenesi",
    "Company": "Cantina Valtenesi",
    "Style": "Red",
    "ABV": 13,
    "Calories": 120,
    "oz": 5,
    "Origin": "Italy",
    "Rating": 0,
    "Favorites": false
  },
  {
    "Name": "Bianchello del Metauro",
    "Company": "Cantina Bianchello del Metauro",
    "Style": "White",
    "ABV": 12,
    "Calories": 110,
    "oz": 5,
    "Origin": "Italy",
    "Rating": 0,
    "Favorites": false
  },
  {
    "Name": "Colli Maceratesi",
    "Company": "Cantina Colli Maceratesi",
    "Style": "Red",
    "ABV": 13,
    "Calories": 120,
    "oz": 5,
    "Origin": "Italy",
    "Rating": 0,
    "Favorites": false
  },
  {
    "Name": "Colli Pesaresi",
    "Company": "Cantina Colli Pesaresi",
    "Style": "White",
    "ABV": 12,
    "Calories": 110,
    "oz": 5,
    "Origin": "Italy",
    "Rating": 0,
    "Favorites": false
  },
  {
    "Name": "Esino",
    "Company": "Cantina Esino",
    "Style": "Red",
    "ABV": 13,
    "Calories": 120,
    "oz": 5,
    "Origin": "Italy",
    "Rating": 0,
    "Favorites": false
  },
  {
    "Name": "Falerio dei Colli Ascolani",
    "Company": "Cantina Falerio dei Colli Ascolani",
    "Style": "White",
    "ABV": 12,
    "Calories": 110,
    "oz": 5,
    "Origin": "Italy",
    "Rating": 0,
    "Favorites": false
  },
  {
    "Name": "Lacrima di Morro d'Alba",
    "Company": "Cantina Lacrima di Morro d'Alba",
    "Style": "Red",
    "ABV": 13,
    "Calories": 120,
    "oz": 5,
    "Origin": "Italy",
    "Rating": 0,
    "Favorites": false
  },
  {
    "Name": "Offida",
    "Company": "Cantina Offida",
    "Style": "Red",
    "ABV": 13,
    "Calories": 120,
    "oz": 5,
    "Origin": "Italy",
    "Rating": 0,
    "Favorites": false
  },
  {
    "Name": "Pergola",
    "Company": "Cantina Pergola",
    "Style": "Red",
    "ABV": 13,
    "Calories": 120,
    "oz": 5,
    "Origin": "Italy",
    "Rating": 0,
    "Favorites": false
  },
  {
    "Name": "Rosso Conero",
    "Company": "Cantina Rosso Conero",
    "Style": "Red",
    "ABV": 13,
    "Calories": 120,
    "oz": 5,
    "Origin": "Italy",
    "Rating": 0,
    "Favorites": false
  },
  {
    "Name": "Rosso Piceno",
    "Company": "Cantina Rosso Piceno",
    "Style": "Red",
    "ABV": 13,
    "Calories": 120,
    "oz": 5,
    "Origin": "Italy",
    "Rating": 0,
    "Favorites": false
  },
  {
    "Name": "Verdicchio dei Castelli di Jesi",
    "Company": "Cantina Verdicchio dei Castelli di Jesi",
    "Style": "White",
    "ABV": 12,
    "Calories": 110,
    "oz": 5,
    "Origin": "Italy",
    "Rating": 0,
    "Favorites": false
  },
  {
    "Name": "Verdicchio di Matelica",
    "Company": "Cantina Verdicchio di Matelica",
    "Style": "White",
    "ABV": 12,
    "Calories": 110,
    "oz": 5,
    "Origin": "Italy",
    "Rating": 0,
    "Favorites": false
  },
  {
    "Name": "Biferno",
    "Company": "Cantina Biferno",
    "Style": "Red",
    "ABV": 13,
    "Calories": 120,
    "oz": 5,
    "Origin": "Italy",
    "Rating": 0,
    "Favorites": false
  },
  {
    "Name": "Molise",
    "Company": "Cantina Molise",
    "Style": "Red",
    "ABV": 13,
    "Calories": 120,
    "oz": 5,
    "Origin": "Italy",
    "Rating": 0,
    "Favorites": false
  },
  {
    "Name": "Pentro di Isernia",
    "Company": "Cantina Pentro di Isernia",
    "Style": "Red",
    "ABV": 13,
    "Calories": 120,
    "oz": 5,
    "Origin": "Italy",
    "Rating": 0,
    "Favorites": false
  },
  {
    "Name": "Tintilia",
    "Company": "Cantina Tintilia",
    "Style": "Red",
    "ABV": 13,
    "Calories": 120,
    "oz": 5,
    "Origin": "Italy",
    "Rating": 0,
    "Favorites": false
  },
  {
    "Name": "Albugnano",
    "Company": "Cantina Albugnano",
    "Style": "Red",
    "ABV": 13,
    "Calories": 120,
    "oz": 5,
    "Origin": "Italy",
    "Rating": 0,
    "Favorites": false
  },
  {
    "Name": "Alta Langa",
    "Company": "Cantina Alta Langa",
    "Style": "Sparkling",
    "ABV": 12,
    "Calories": 110,
    "oz": 5,
    "Origin": "Italy",
    "Rating": 0,
    "Favorites": false
  },
  {
    "Name": "Barbera d'Alba",
    "Company": "Cantina Barbera d'Alba",
    "Style": "Red",
    "ABV": 13,
    "Calories": 120,
    "oz": 5,
    "Origin": "Italy",
    "Rating": 0,
    "Favorites": false
  },
  {
    "Name": "Barbera d'Asti",
    "Company": "Cantina Barbera d'Asti",
    "Style": "Red",
    "ABV": 13,
    "Calories": 120,
    "oz": 5,
    "Origin": "Italy",
    "Rating": 0,
    "Favorites": false
  },
  {
    "Name": "Barbera del Monferrato",
    "Company": "Cantina Barbera del Monferrato",
    "Style": "Red",
    "ABV": 13,
    "Calories": 120,
    "oz": 5,
    "Origin": "Italy",
    "Rating": 0,
    "Favorites": false
  },
  {
    "Name": "Boca",
    "Company": "Cantina Boca",
    "Style": "Red",
    "ABV": 13,
    "Calories": 120,
    "oz": 5,
    "Origin": "Italy",
    "Rating": 0,
    "Favorites": false
  },
  {
    "Name": "Bramaterra",
    "Company": "Cantina Bramaterra",
    "Style": "Red",
    "ABV": 13,
    "Calories": 120,
    "oz": 5,
    "Origin": "Italy",
    "Rating": 0,
    "Favorites": false
  },
  {
    "Name": "Calosso",
    "Company": "Cantina Calosso",
    "Style": "Red",
    "ABV": 13,
    "Calories": 120,
    "oz": 5,
    "Origin": "Italy",
    "Rating": 0,
    "Favorites": false
  },
  {
    "Name": "Canavese",
    "Company": "Cantina Canavese",
    "Style": "Red",
    "ABV": 13,
    "Calories": 120,
    "oz": 5,
    "Origin": "Italy",
    "Rating": 0,
    "Favorites": false
  },
  {
    "Name": "Carema",
    "Company": "Cantina Carema",
    "Style": "Red",
    "ABV": 13,
    "Calories": 120,
    "oz": 5,
    "Origin": "Italy",
    "Rating": 0,
    "Favorites": false
  },
  {
    "Name": "Cisterna d'Asti",
    "Company": "Cantina Cisterna d'Asti",
    "Style": "Red",
    "ABV": 13,
    "Calories": 120,
    "oz": 5,
    "Origin": "Italy",
    "Rating": 0,
    "Favorites": false
  },
  {
    "Name": "Colli Tortonesi",
    "Company": "Cantina Colli Tortonesi",
    "Style": "Red",
    "ABV": 13,
    "Calories": 120,
    "oz": 5,
    "Origin": "Italy",
    "Rating": 0,
    "Favorites": false
  },
  {
    "Name": "Collina Torinese",
    "Company": "Cantina Collina Torinese",
    "Style": "Red",
    "ABV": 13,
    "Calories": 120,
    "oz": 5,
    "Origin": "Italy",
    "Rating": 0,
    "Favorites": false
  },
  {
    "Name": "Colline Novaresi",
    "Company": "Cantina Colline Novaresi",
    "Style": "Red",
    "ABV": 13,
    "Calories": 120,
    "oz": 5,
    "Origin": "Italy",
    "Rating": 0,
    "Favorites": false
  },
  {
    "Name": "Colline Saluzzesi",
    "Company": "Cantina Colline Saluzzesi",
    "Style": "Red",
    "ABV": 13,
    "Calories": 120,
    "oz": 5,
    "Origin": "Italy",
    "Rating": 0,
    "Favorites": false
  },
  {
    "Name": "Cortese dell'Alto Monferrato",
    "Company": "Cantina Cortese dell'Alto Monferrato",
    "Style": "White",
    "ABV": 12,
    "Calories": 110,
    "oz": 5,
    "Origin": "Italy",
    "Rating": 0,
    "Favorites": false
  },
  {
    "Name": "Coste della Sesia",
    "Company": "Cantina Coste della Sesia",
    "Style": "Red",
    "ABV": 13,
    "Calories": 120,
    "oz": 5,
    "Origin": "Italy",
    "Rating": 0,
    "Favorites": false
  },
  {
    "Name": "Dolcetto d'Acqui",
    "Company": "Cantina Dolcetto d'Acqui",
    "Style": "Red",
    "ABV": 13,
    "Calories": 120,
    "oz": 5,
    "Origin": "Italy",
    "Rating": 0,
    "Favorites": false
  },
  {
    "Name": "Dolcetto d'Alba",
    "Company": "Cantina Dolcetto d'Alba",
    "Style": "Red",
    "ABV": 13,
    "Calories": 120,
    "oz": 5,
    "Origin": "Italy",
    "Rating": 0,
    "Favorites": false
  },
  {
    "Name": "Dolcetto d'Asti",
    "Company": "Cantina Dolcetto d'Asti",
    "Style": "Red",
    "ABV": 13,
    "Calories": 120,
    "oz": 5,
    "Origin": "Italy",
    "Rating": 0,
    "Favorites": false
  },
  {
    "Name": "Dolcetto delle Langhe Monregalesi",
    "Company": "Cantina Dolcetto delle Langhe Monregalesi",
    "Style": "Red",
    "ABV": 13,
    "Calories": 120,
    "oz": 5,
    "Origin": "Italy",
    "Rating": 0,
    "Favorites": false
  },
  {
    "Name": "Dolcetto di Diano d'Alba",
    "Company": "Cantina Dolcetto di Diano d'Alba",
    "Style": "Red",
    "ABV": 13,
    "Calories": 120,
    "oz": 5,
    "Origin": "Italy",
    "Rating": 0,
    "Favorites": false
  },
  {
    "Name": "Dolcetto di Dogliani",
    "Company": "Cantina Dolcetto di Dogliani",
    "Style": "Red",
    "ABV": 13,
    "Calories": 120,
    "oz": 5,
    "Origin": "Italy",
    "Rating": 0,
    "Favorites": false
  },
  {
    "Name": "Dolcetto di Ovada",
    "Company": "Cantina Dolcetto di Ovada",
    "Style": "Red",
    "ABV": 13,
    "Calories": 120,
    "oz": 5,
    "Origin": "Italy",
    "Rating": 0,
    "Favorites": false
  },
  {
    "Name": "Erbaluce di Caluso",
    "Company": "Cantina Erbaluce di Caluso",
    "Style": "White",
    "ABV": 12,
    "Calories": 110,
    "oz": 5,
    "Origin": "Italy",
    "Rating": 0,
    "Favorites": false
  },
  {
    "Name": "Fara",
    "Company": "Cantina Fara",
    "Style": "Red",
    "ABV": 13,
    "Calories": 120,
    "oz": 5,
    "Origin": "Italy",
    "Rating": 0,
    "Favorites": false
  },
  {
    "Name": "Freisa d'Asti",
    "Company": "Cantina Freisa d'Asti",
    "Style": "Red",
    "ABV": 13,
    "Calories": 120,
    "oz": 5,
    "Origin": "Italy",
    "Rating": 0,
    "Favorites": false
  },
  {
    "Name": "Freisa di Chieri",
    "Company": "Cantina Freisa di Chieri",
    "Style": "Red",
    "ABV": 13,
    "Calories": 120,
    "oz": 5,
    "Origin": "Italy",
    "Rating": 0,
    "Favorites": false
  },
  {
    "Name": "Gabiano",
    "Company": "Cantina Gabiano",
    "Style": "Red",
    "ABV": 13,
    "Calories": 120,
    "oz": 5,
    "Origin": "Italy",
    "Rating": 0,
    "Favorites": false
  },
  {
    "Name": "Grignolino d'Asti",
    "Company": "Cantina Grignolino d'Asti",
    "Style": "Red",
    "ABV": 13,
    "Calories": 120,
    "oz": 5,
    "Origin": "Italy",
    "Rating": 0,
    "Favorites": false
  },
  {
    "Name": "Grignolino del Monferrato Casalese",
    "Company": "Cantina Grignolino del Monferrato Casalese",
    "Style": "Red",
    "ABV": 13,
    "Calories": 120,
    "oz": 5,
    "Origin": "Italy",
    "Rating": 0,
    "Favorites": false
  },
  {
    "Name": "Langhe",
    "Company": "Cantina Langhe",
    "Style": "Red",
    "ABV": 13,
    "Calories": 120,
    "oz": 5,
    "Origin": "Italy",
    "Rating": 0,
    "Favorites": false
  },
  {
    "Name": "Lessona",
    "Company": "Cantina Lessona",
    "Style": "Red",
    "ABV": 13,
    "Calories": 120,
    "oz": 5,
    "Origin": "Italy",
    "Rating": 0,
    "Favorites": false
  },
  {
    "Name": "Loazzolo",
    "Company": "Cantina Loazzolo",
    "Style": "White",
    "ABV": 12,
    "Calories": 110,
    "oz": 5,
    "Origin": "Italy",
    "Rating": 0,
    "Favorites": false
  },
  {
    "Name": "Malvasia di Casorzo d'Asti",
    "Company": "Cantina Malvasia di Casorzo d'Asti",
    "Style": "Red",
    "ABV": 13,
    "Calories": 120,
    "oz": 5,
    "Origin": "Italy",
    "Rating": 0,
    "Favorites": false
  },
  {
    "Name": "Malvasia di Castelnuovo Don Bosco",
    "Company": "Cantina Malvasia di Castelnuovo Don Bosco",
    "Style": "Red",
    "ABV": 13,
    "Calories": 120,
    "oz": 5,
    "Origin": "Italy",
    "Rating": 0,
    "Favorites": false
  },
  {
    "Name": "Monferrato",
    "Company": "Cantina Monferrato",
    "Style": "Red",
    "ABV": 13,
    "Calories": 120,
    "oz": 5,
    "Origin": "Italy",
    "Rating": 0,
    "Favorites": false
  },
  {
    "Name": "Nebbiolo d'Alba",
    "Company": "Cantina Nebbiolo d'Alba",
    "Style": "Red",
    "ABV": 13,
    "Calories": 120,
    "oz": 5,
    "Origin": "Italy",
    "Rating": 0,
    "Favorites": false
  },
  {
    "Name": "Piemonte",
    "Company": "Cantina Piemonte",
    "Style": "Red",
    "ABV": 13,
    "Calories": 120,
    "oz": 5,
    "Origin": "Italy",
    "Rating": 0,
    "Favorites": false
  },
  {
    "Name": "Pinerolese",
    "Company": "Cantina Pinerolese",
    "Style": "Red",
    "ABV": 13,
    "Calories": 120,
    "oz": 5,
    "Origin": "Italy",
    "Rating": 0,
    "Favorites": false
  },
  {
    "Name": "Rubino di Cantavenna",
    "Company": "Cantina Rubino di Cantavenna",
    "Style": "Red",
    "ABV": 13,
    "Calories": 120,
    "oz": 5,
    "Origin": "Italy",
    "Rating": 0,
    "Favorites": false
  },
  {
    "Name": "Ruché di Castagnole Monferrato",
    "Company": "Cantina Ruché di Castagnole Monferrato",
    "Style": "Red",
    "ABV": 13,
    "Calories": 120,
    "oz": 5,
    "Origin": "Italy",
    "Rating": 0,
    "Favorites": false
  },
  {
    "Name": "Sizzano",
    "Company": "Cantina Sizzano",
    "Style": "Red",
    "ABV": 13,
    "Calories": 120,
    "oz": 5,
    "Origin": "Italy",
    "Rating": 0,
    "Favorites": false
  },
  {
    "Name": "Valsusa",
    "Company": "Cantina Valsusa",
    "Style": "Red",
    "ABV": 13,
    "Calories": 120,
    "oz": 5,
    "Origin": "Italy",
    "Rating": 0,
    "Favorites": false
  },
  {
    "Name": "Verduno Pelaverga",
    "Company": "Cantina Verduno Pelaverga",
    "Style": "Red",
    "ABV": 13,
    "Calories": 120,
    "oz": 5,
    "Origin": "Italy",
    "Rating": 0,
    "Favorites": false
  },
  {
    "Name": "Aleatico di Puglia",
    "Company": "Cantina Aleatico di Puglia",
    "Style": "Red",
    "ABV": 14,
    "Calories": 125,
    "oz": 5,
    "Origin": "Italy",
    "Rating": 0,
    "Favorites": false
  },
  {
    "Name": "Alezio",
    "Company": "Cantina Alezio",
    "Style": "Red",
    "ABV": 13,
    "Calories": 120,
    "oz": 5,
    "Origin": "Italy",
    "Rating": 0,
    "Favorites": false
  },
  {
    "Name": "Barletta",
    "Company": "Cantina Barletta",
    "Style": "Red",
    "ABV": 13,
    "Calories": 120,
    "oz": 5,
    "Origin": "Italy",
    "Rating": 0,
    "Favorites": false
  },
  {
    "Name": "Brindisi",
    "Company": "Cantina Brindisi",
    "Style": "Red",
    "ABV": 13,
    "Calories": 120,
    "oz": 5,
    "Origin": "Italy",
    "Rating": 0,
    "Favorites": false
  },
  {
    "Name": "Cacc'e mmitte di Lucera",
    "Company": "Cantina Cacc'e mmitte di Lucera",
    "Style": "Red",
    "ABV": 13,
    "Calories": 120,
    "oz": 5,
    "Origin": "Italy",
    "Rating": 0,
    "Favorites": false
  },
  {
    "Name": "Castel del Monte",
    "Company": "Cantina Castel del Monte",
    "Style": "Red",
    "ABV": 13,
    "Calories": 120,
    "oz": 5,
    "Origin": "Italy",
    "Rating": 0,
    "Favorites": false
  },
  {
    "Name": "Colline Joniche Taratine",
    "Company": "Cantina Colline Joniche Taratine",
    "Style": "Red",
    "ABV": 13,
    "Calories": 120,
    "oz": 5,
    "Origin": "Italy",
    "Rating": 0,
    "Favorites": false
  },
  {
    "Name": "Copertino",
    "Company": "Cantina Copertino",
    "Style": "Red",
    "ABV": 13,
    "Calories": 120,
    "oz": 5,
    "Origin": "Italy",
    "Rating": 0,
    "Favorites": false
  },
  {
    "Name": "Galatina",
    "Company": "Cantina Galatina",
    "Style": "Red",
    "ABV": 13,
    "Calories": 120,
    "oz": 5,
    "Origin": "Italy",
    "Rating": 0,
    "Favorites": false
  },
  {
    "Name": "Gioia del Colle",
    "Company": "Cantina Gioia del Colle",
    "Style": "Red",
    "ABV": 13,
    "Calories": 120,
    "oz": 5,
    "Origin": "Italy",
    "Rating": 0,
    "Favorites": false
  },
  {
    "Name": "Gravina",
    "Company": "Cantina Gravina",
    "Style": "White",
    "ABV": 12,
    "Calories": 110,
    "oz": 5,
    "Origin": "Italy",
    "Rating": 0,
    "Favorites": false
  },
  {
    "Name": "Leverano",
    "Company": "Cantina Leverano",
    "Style": "Red",
    "ABV": 13,
    "Calories": 120,
    "oz": 5,
    "Origin": "Italy",
    "Rating": 0,
    "Favorites": false
  },
  {
    "Name": "Lizzano",
    "Company": "Cantina Lizzano",
    "Style": "Red",
    "ABV": 13,
    "Calories": 120,
    "oz": 5,
    "Origin": "Italy",
    "Rating": 0,
    "Favorites": false
  },
  {
    "Name": "Locorotondo",
    "Company": "Cantina Locorotondo",
    "Style": "White",
    "ABV": 12,
    "Calories": 110,
    "oz": 5,
    "Origin": "Italy",
    "Rating": 0,
    "Favorites": false
  },
  {
    "Name": "Martina",
    "Company": "Cantina Martina",
    "Style": "Red",
    "ABV": 13,
    "Calories": 120,
    "oz": 5,
    "Origin": "Italy",
    "Rating": 0,
    "Favorites": false
  },
  {
    "Name": "Matino",
    "Company": "Cantina Matino",
    "Style": "Red",
    "ABV": 13,
    "Calories": 120,
    "oz": 5,
    "Origin": "Italy",
    "Rating": 0,
    "Favorites": false
  },
  {
    "Name": "Moscato di Trani",
    "Company": "Cantina Moscato di Trani",
    "Style": "White",
    "ABV": 12,
    "Calories": 110,
    "oz": 5,
    "Origin": "Italy",
    "Rating": 0,
    "Favorites": false
  },
  {
    "Name": "Nardò",
    "Company": "Cantina Nardò",
    "Style": "Red",
    "ABV": 13,
    "Calories": 120,
    "oz": 5,
    "Origin": "Italy",
    "Rating": 0,
    "Favorites": false
  },
  {
    "Name": "Negroamaro di Terra d'Otranto",
    "Company": "Cantina Negroamaro di Terra d'Otranto",
    "Style": "Red",
    "ABV": 13,
    "Calories": 120,
    "oz": 5,
    "Origin": "Italy",
    "Rating": 0,
    "Favorites": false
  },
  {
    "Name": "Orta Nova",
    "Company": "Cantina Orta Nova",
    "Style": "Red",
    "ABV": 13,
    "Calories": 120,
    "oz": 5,
    "Origin": "Italy",
    "Rating": 0,
    "Favorites": false
  },
  {
    "Name": "Ostuni",
    "Company": "Cantina Ostuni",
    "Style": "White",
    "ABV": 12,
    "Calories": 110,
    "oz": 5,
    "Origin": "Italy",
    "Rating": 0,
    "Favorites": false
  },
  {
    "Name": "Primitivo di Manduria",
    "Company": "Cantina Primitivo di Manduria",
    "Style": "Red",
    "ABV": 14,
    "Calories": 125,
    "oz": 5,
    "Origin": "Italy",
    "Rating": 0,
    "Favorites": false
  },
  {
    "Name": "Rosso Barletta",
    "Company": "Cantina Rosso Barletta",
    "Style": "Red",
    "ABV": 13,
    "Calories": 120,
    "oz": 5,
    "Origin": "Italy",
    "Rating": 0,
    "Favorites": false
  },
  {
    "Name": "Rosso Canosa",
    "Company": "Cantina Rosso Canosa",
    "Style": "Red",
    "ABV": 13,
    "Calories": 120,
    "oz": 5,
    "Origin": "Italy",
    "Rating": 0,
    "Favorites": false
  },
  {
    "Name": "Rosso di Cerignola",
    "Company": "Cantina Rosso di Cerignola",
    "Style": "Red",
    "ABV": 13,
    "Calories": 120,
    "oz": 5,
    "Origin": "Italy",
    "Rating": 0,
    "Favorites": false
  },
  {
    "Name": "Salice Salentino",
    "Company": "Cantina Salice Salentino",
    "Style": "Red",
    "ABV": 13,
    "Calories": 120,
    "oz": 5,
    "Origin": "Italy",
    "Rating": 0,
    "Favorites": false
  },
  {
    "Name": "San Severo",
    "Company": "Cantina San Severo",
    "Style": "Red",
    "ABV": 13,
    "Calories": 120,
    "oz": 5,
    "Origin": "Italy",
    "Rating": 0,
    "Favorites": false
  },
  {
    "Name": "Squinzano",
    "Company": "Cantina Squinzano",
    "Style": "Red",
    "ABV": 13,
    "Calories": 120,
    "oz": 5,
    "Origin": "Italy",
    "Rating": 0,
    "Favorites": false
  },
  {
    "Name": "Tavoliere delle Puglie",
    "Company": "Cantina Tavoliere delle Puglie",
    "Style": "Red",
    "ABV": 13,
    "Calories": 120,
    "oz": 5,
    "Origin": "Italy",
    "Rating": 0,
    "Favorites": false
  },
  {
    "Name": "Terra d'Otranto",
    "Company": "Cantina Terra d'Otranto",
    "Style": "Red",
    "ABV": 13,
    "Calories": 120,
    "oz": 5,
    "Origin": "Italy",
    "Rating": 0,
    "Favorites": false
  },
  {
    "Name": "Alghero",
    "Company": "Cantina Alghero",
    "Style": "Red",
    "ABV": 13,
    "Calories": 120,
    "oz": 5,
    "Origin": "Italy",
    "Rating": 0,
    "Favorites": false
  },
  {
    "Name": "Arborea",
    "Company": "Cantina Arborea",
    "Style": "Red",
    "ABV": 13,
    "Calories": 120,
    "oz": 5,
    "Origin": "Italy",
    "Rating": 0,
    "Favorites": false
  },
  {
    "Name": "Campidano di Terralba",
    "Company": "Cantina Campidano di Terralba",
    "Style": "Red",
    "ABV": 13,
    "Calories": 120,
    "oz": 5,
    "Origin": "Italy",
    "Rating": 0,
    "Favorites": false
  },
  {
    "Name": "Cannonau di Sardegna",
    "Company": "Cantina Cannonau di Sardegna",
    "Style": "Red",
    "ABV": 13,
    "Calories": 120,
    "oz": 5,
    "Origin": "Italy",
    "Rating": 0,
    "Favorites": false
  },
  {
    "Name": "Carignano del Sulcis",
    "Company": "Cantina Carignano del Sulcis",
    "Style": "Red",
    "ABV": 13,
    "Calories": 120,
    "oz": 5,
    "Origin": "Italy",
    "Rating": 0,
    "Favorites": false
  },
  {
    "Name": "Girò di Cagliari",
    "Company": "Cantina Girò di Cagliari",
    "Style": "Red",
    "ABV": 13,
    "Calories": 120,
    "oz": 5,
    "Origin": "Italy",
    "Rating": 0,
    "Favorites": false
  },
  {
    "Name": "Malvasia di Bosa",
    "Company": "Cantina Malvasia di Bosa",
    "Style": "White",
    "ABV": 12,
    "Calories": 110,
    "oz": 5,
    "Origin": "Italy",
    "Rating": 0,
    "Favorites": false
  },
  {
    "Name": "Malvasia di Cagliari",
    "Company": "Cantina Malvasia di Cagliari",
    "Style": "White",
    "ABV": 12,
    "Calories": 110,
    "oz": 5,
    "Origin": "Italy",
    "Rating": 0,
    "Favorites": false
  },
  {
    "Name": "Mandrolisai",
    "Company": "Cantina Mandrolisai",
    "Style": "Red",
    "ABV": 13,
    "Calories": 120,
    "oz": 5,
    "Origin": "Italy",
    "Rating": 0,
    "Favorites": false
  },
  {
    "Name": "Monica di Cagliari",
    "Company": "Cantina Monica di Cagliari",
    "Style": "Red",
    "ABV": 13,
    "Calories": 120,
    "oz": 5,
    "Origin": "Italy",
    "Rating": 0,
    "Favorites": false
  },
  {
    "Name": "Monica di Sardegna",
    "Company": "Cantina Monica di Sardegna",
    "Style": "Red",
    "ABV": 13,
    "Calories": 120,
    "oz": 5,
    "Origin": "Italy",
    "Rating": 0,
    "Favorites": false
  },
  {
    "Name": "Moscato di Cagliari",
    "Company": "Cantina Moscato di Cagliari",
    "Style": "White",
    "ABV": 12,
    "Calories": 110,
    "oz": 5,
    "Origin": "Italy",
    "Rating": 0,
    "Favorites": false
  },
  {
    "Name": "Moscato di Sardegna",
    "Company": "Cantina Moscato di Sardegna",
    "Style": "White",
    "ABV": 12,
    "Calories": 110,
    "oz": 5,
    "Origin": "Italy",
    "Rating": 0,
    "Favorites": false
  },
  {
    "Name": "Moscato di Sorso Sennori",
    "Company": "Cantina Moscato di Sorso Sennori",
    "Style": "White",
    "ABV": 12,
    "Calories": 110,
    "oz": 5,
    "Origin": "Italy",
    "Rating": 0,
    "Favorites": false
  },
  {
    "Name": "Nasco di Cagliari",
    "Company": "Cantina Nasco di Cagliari",
    "Style": "White",
    "ABV": 12,
    "Calories": 110,
    "oz": 5,
    "Origin": "Italy",
    "Rating": 0,
    "Favorites": false
  },
  {
    "Name": "Nuragus di Cagliari",
    "Company": "Cantina Nuragus di Cagliari",
    "Style": "White",
    "ABV": 12,
    "Calories": 110,
    "oz": 5,
    "Origin": "Italy",
    "Rating": 0,
    "Favorites": false
  },
  {
    "Name": "Sardegna Semidano",
    "Company": "Cantina Sardegna Semidano",
    "Style": "White",
    "ABV": 12,
    "Calories": 110,
    "oz": 5,
    "Origin": "Italy",
    "Rating": 0,
    "Favorites": false
  },
  {
    "Name": "Vermentino di Sardegna",
    "Company": "Cantina Vermentino di Sardegna",
    "Style": "White",
    "ABV": 12,
    "Calories": 110,
    "oz": 5,
    "Origin": "Italy",
    "Rating": 0,
    "Favorites": false
  },
  {
    "Name": "Vernaccia di Oristano",
    "Company": "Cantina Vernaccia di Oristano",
    "Style": "White",
    "ABV": 12,
    "Calories": 110,
    "oz": 5,
    "Origin": "Italy",
    "Rating": 0,
    "Favorites": false
  },
  {
    "Name": "Alcamo",
    "Company": "Cantina Alcamo",
    "Style": "White",
    "ABV": 12,
    "Calories": 110,
    "oz": 5,
    "Origin": "Italy",
    "Rating": 0,
    "Favorites": false
  },
  {
    "Name": "Contea di Sclafani",
    "Company": "Cantina Contea di Sclafani",
    "Style": "Red",
    "ABV": 13,
    "Calories": 120,
    "oz": 5,
    "Origin": "Italy",
    "Rating": 0,
    "Favorites": false
  },
  {
    "Name": "Contessa Entellina",
    "Company": "Cantina Contessa Entellina",
    "Style": "Red",
    "ABV": 13,
    "Calories": 120,
    "oz": 5,
    "Origin": "Italy",
    "Rating": 0,
    "Favorites": false
  },
  {
    "Name": "Delia Nivolelli",
    "Company": "Cantina Delia Nivolelli",
    "Style": "Red",
    "ABV": 13,
    "Calories": 120,
    "oz": 5,
    "Origin": "Italy",
    "Rating": 0,
    "Favorites": false
  },
  {
    "Name": "Eloro",
    "Company": "Cantina Eloro",
    "Style": "Red",
    "ABV": 13,
    "Calories": 120,
    "oz": 5,
    "Origin": "Italy",
    "Rating": 0,
    "Favorites": false
  },
  {
    "Name": "Erice",
    "Company": "Cantina Erice",
    "Style": "Red",
    "ABV": 13,
    "Calories": 120,
    "oz": 5,
    "Origin": "Italy",
    "Rating": 0,
    "Favorites": false
  },
  {
    "Name": "Etna",
    "Company": "Cantina Etna",
    "Style": "Red",
    "ABV": 13,
    "Calories": 120,
    "oz": 5,
    "Origin": "Italy",
    "Rating": 0,
    "Favorites": false
  },
  {
    "Name": "Faro",
    "Company": "Cantina Faro",
    "Style": "Red",
    "ABV": 13,
    "Calories": 120,
    "oz": 5,
    "Origin": "Italy",
    "Rating": 0,
    "Favorites": false
  },
  {
    "Name": "Malvasia delle Lipari",
    "Company": "Cantina Malvasia delle Lipari",
    "Style": "White",
    "ABV": 12,
    "Calories": 110,
    "oz": 5,
    "Origin": "Italy",
    "Rating": 0,
    "Favorites": false
  },
  {
    "Name": "Mamertino di Milazzo",
    "Company": "Cantina Mamertino di Milazzo",
    "Style": "Red",
    "ABV": 13,
    "Calories": 120,
    "oz": 5,
    "Origin": "Italy",
    "Rating": 0,
    "Favorites": false
  },
  {
    "Name": "Marsala",
    "Company": "Cantina Marsala",
    "Style": "White",
    "ABV": 15,
    "Calories": 130,
    "oz": 5,
    "Origin": "Italy",
    "Rating": 0,
    "Favorites": false
  },
  {
    "Name": "Menfi",
    "Company": "Cantina Menfi",
    "Style": "Red",
    "ABV": 13,
    "Calories": 120,
    "oz": 5,
    "Origin": "Italy",
    "Rating": 0,
    "Favorites": false
  },
  {
    "Name": "Monreale",
    "Company": "Cantina Monreale",
    "Style": "Red",
    "ABV": 13,
    "Calories": 120,
    "oz": 5,
    "Origin": "Italy",
    "Rating": 0,
    "Favorites": false
  },
  {
    "Name": "Noto",
    "Company": "Cantina Noto",
    "Style": "Red",
    "ABV": 13,
    "Calories": 120,
    "oz": 5,
    "Origin": "Italy",
    "Rating": 0,
    "Favorites": false
  },
  {
    "Name": "Moscato di Pantelleria",
    "Company": "Cantina Pantelleria",
    "Style": "White",
    "ABV": 12,
    "Calories": 110,
    "oz": 5,
    "Origin": "Italy",
    "Rating": 0,
    "Favorites": false
  },
  {
    "Name": "Moscato di Siracusa",
    "Company": "Cantina Siracusa",
    "Style": "White",
    "ABV": 12,
    "Calories": 110,
    "oz": 5,
    "Origin": "Italy",
    "Rating": 0,
    "Favorites": false
  },
  {
    "Name": "Riesi",
    "Company": "Cantina Riesi",
    "Style": "Red",
    "ABV": 13,
    "Calories": 120,
    "oz": 5,
    "Origin": "Italy",
    "Rating": 0,
    "Favorites": false
  },
  {
    "Name": "Salaparuta",
    "Company": "Cantina Salaparuta",
    "Style": "Red",
    "ABV": 13,
    "Calories": 120,
    "oz": 5,
    "Origin": "Italy",
    "Rating": 0,
    "Favorites": false
  },
  {
    "Name": "Sambuca di Sicilia",
    "Company": "Cantina Sambuca di Sicilia",
    "Style": "Red",
    "ABV": 13,
    "Calories": 120,
    "oz": 5,
    "Origin": "Italy",
    "Rating": 0,
    "Favorites": false
  },
  {
    "Name": "Santa Margherita di Belice",
    "Company": "Cantina Santa Margherita di Belice",
    "Style": "Red",
    "ABV": 13,
    "Calories": 120,
    "oz": 5,
    "Origin": "Italy",
    "Rating": 0,
    "Favorites": false
  },
  {
    "Name": "Sciacca",
    "Company": "Cantina Sciacca",
    "Style": "Red",
    "ABV": 13,
    "Calories": 120,
    "oz": 5,
    "Origin": "Italy",
    "Rating": 0,
    "Favorites": false
  },
  {
    "Name": "Siracusa",
    "Company": "Cantina Siracusa",
    "Style": "Red",
    "ABV": 13,
    "Calories": 120,
    "oz": 5,
    "Origin": "Italy",
    "Rating": 0,
    "Favorites": false
  },
  {
    "Name": "Vittoria",
    "Company": "Cantina Vittoria",
    "Style": "Red",
    "ABV": 13,
    "Calories": 120,
    "oz": 5,
    "Origin": "Italy",
    "Rating": 0,
    "Favorites": false
  },
  {
    "Name": "Ansonica Costa dell'Argentario",
    "Company": "Cantina Costa dell'Argentario",
    "Style": "White",
    "ABV": 12,
    "Calories": 110,
    "oz": 5,
    "Origin": "Italy",
    "Rating": 0,
    "Favorites": false
  },
  {
    "Name": "Barco Reale di Carmignano",
    "Company": "Cantina Carmignano",
    "Style": "Red",
    "ABV": 13,
    "Calories": 120,
    "oz": 5,
    "Origin": "Italy",
    "Rating": 0,
    "Favorites": false
  },
  {
    "Name": "Bianco della Valdinievole",
    "Company": "Cantina Valdinievole",
    "Style": "White",
    "ABV": 11,
    "Calories": 100,
    "oz": 5,
    "Origin": "Italy",
    "Rating": 0,
    "Favorites": false
  },
  {
    "Name": "Bianco dell'Empolese",
    "Company": "Cantina dell'Empolese",
    "Style": "White",
    "ABV": 11,
    "Calories": 100,
    "oz": 5,
    "Origin": "Italy",
    "Rating": 0,
    "Favorites": false
  },
  {
    "Name": "Bianco di Pitigliano",
    "Company": "Cantina Pitigliano",
    "Style": "White",
    "ABV": 12,
    "Calories": 110,
    "oz": 5,
    "Origin": "Italy",
    "Rating": 0,
    "Favorites": false
  },
  {
    "Name": "Bianco Pisano di San Torpè",
    "Company": "Cantina San Torpè",
    "Style": "White",
    "ABV": 11,
    "Calories": 100,
    "oz": 5,
    "Origin": "Italy",
    "Rating": 0,
    "Favorites": false
  },
  {
    "Name": "Bianco Vergine della Valdichiana",
    "Company": "Cantina Valdichiana",
    "Style": "White",
    "ABV": 11,
    "Calories": 100,
    "oz": 5,
    "Origin": "Italy",
    "Rating": 0,
    "Favorites": false
  },
  {
    "Name": "Bolgheri",
    "Company": "Cantina Bolgheri",
    "Style": "Red",
    "ABV": 13,
    "Calories": 120,
    "oz": 5,
    "Origin": "Italy",
    "Rating": 0,
    "Favorites": false
  },
  {
    "Name": "Candia dei Colli Apuani",
    "Company": "Cantina Colli Apuani",
    "Style": "White",
    "ABV": 11,
    "Calories": 100,
    "oz": 5,
    "Origin": "Italy",
    "Rating": 0,
    "Favorites": false
  },
  {
    "Name": "Capalbio",
    "Company": "Cantina Capalbio",
    "Style": "Red",
    "ABV": 13,
    "Calories": 120,
    "oz": 5,
    "Origin": "Italy",
    "Rating": 0,
    "Favorites": false
  },
  {
    "Name": "Colli dell'Etruria Centrale",
    "Company": "Cantina Etruria Centrale",
    "Style": "Red",
    "ABV": 13,
    "Calories": 120,
    "oz": 5,
    "Origin": "Italy",
    "Rating": 0,
    "Favorites": false
  },
  {
    "Name": "Colli di Luni",
    "Company": "Cantina Luni",
    "Style": "Red",
    "ABV": 13,
    "Calories": 120,
    "oz": 5,
    "Origin": "Italy",
    "Rating": 0,
    "Favorites": false
  },
  {
    "Name": "Colline Lucchesi",
    "Company": "Cantina Lucchesi",
    "Style": "Red",
    "ABV": 13,
    "Calories": 120,
    "oz": 5,
    "Origin": "Italy",
    "Rating": 0,
    "Favorites": false
  },
  {
    "Name": "Cortona",
    "Company": "Cantina Cortona",
    "Style": "Red",
    "ABV": 13,
    "Calories": 120,
    "oz": 5,
    "Origin": "Italy",
    "Rating": 0,
    "Favorites": false
  },
  {
    "Name": "Elba",
    "Company": "Cantina Elba",
    "Style": "Red",
    "ABV": 13,
    "Calories": 120,
    "oz": 5,
    "Origin": "Italy",
    "Rating": 0,
    "Favorites": false
  },
  {
    "Name": "Maremma Toscana",
    "Company": "Cantina Maremma Toscana",
    "Style": "Red",
    "ABV": 13,
    "Calories": 120,
    "oz": 5,
    "Origin": "Italy",
    "Rating": 0,
    "Favorites": false
  },
  {
    "Name": "Montecarlo",
    "Company": "Cantina Montecarlo",
    "Style": "Red",
    "ABV": 13,
    "Calories": 120,
    "oz": 5,
    "Origin": "Italy",
    "Rating": 0,
    "Favorites": false
  },
  {
    "Name": "Montecucco",
    "Company": "Cantina Montecucco",
    "Style": "Red",
    "ABV": 13,
    "Calories": 120,
    "oz": 5,
    "Origin": "Italy",
    "Rating": 0,
    "Favorites": false
  },
  {
    "Name": "Monteregio di Massa Marittima",
    "Company": "Cantina Massa Marittima",
    "Style": "Red",
    "ABV": 13,
    "Calories": 120,
    "oz": 5,
    "Origin": "Italy",
    "Rating": 0,
    "Favorites": false
  },
  {
    "Name": "Montescudaio",
    "Company": "Cantina Montescudaio",
    "Style": "Red",
    "ABV": 13,
    "Calories": 120,
    "oz": 5,
    "Origin": "Italy",
    "Rating": 0,
    "Favorites": false
  },
  {
    "Name": "Moscadello di Montalcino",
    "Company": "Cantina Montalcino",
    "Style": "White",
    "ABV": 12,
    "Calories": 110,
    "oz": 5,
    "Origin": "Italy",
    "Rating": 0,
    "Favorites": false
  },
  {
    "Name": "Orcia",
    "Company": "Cantina Orcia",
    "Style": "Red",
    "ABV": 13,
    "Calories": 120,
    "oz": 5,
    "Origin": "Italy",
    "Rating": 0,
    "Favorites": false
  },
  {
    "Name": "Parrina",
    "Company": "Cantina Parrina",
    "Style": "Red",
    "ABV": 13,
    "Calories": 120,
    "oz": 5,
    "Origin": "Italy",
    "Rating": 0,
    "Favorites": false
  },
  {
    "Name": "Pomino",
    "Company": "Cantina Pomino",
    "Style": "Red",
    "ABV": 13,
    "Calories": 120,
    "oz": 5,
    "Origin": "Italy",
    "Rating": 0,
    "Favorites": false
  },
  {
    "Name": "Rosso di Montalcino",
    "Company": "Cantina Montalcino",
    "Style": "Red",
    "ABV": 13,
    "Calories": 120,
    "oz": 5,
    "Origin": "Italy",
    "Rating": 0,
    "Favorites": false
  },
  {
    "Name": "Rosso di Montepulciano",
    "Company": "Cantina Montepulciano",
    "Style": "Red",
    "ABV": 13,
    "Calories": 120,
    "oz": 5,
    "Origin": "Italy",
    "Rating": 0,
    "Favorites": false
  },
  {
    "Name": "San Gimignano",
    "Company": "Cantina San Gimignano",
    "Style": "White",
    "ABV": 12,
    "Calories": 110,
    "oz": 5,
    "Origin": "Italy",
    "Rating": 0,
    "Favorites": false
  },
  {
    "Name": "Sant'Antimo",
    "Company": "Cantina Sant'Antimo",
    "Style": "Red",
    "ABV": 13,
    "Calories": 120,
    "oz": 5,
    "Origin": "Italy",
    "Rating": 0,
    "Favorites": false
  },
  {
    "Name": "Sovana",
    "Company": "Cantina Sovana",
    "Style": "Red",
    "ABV": 13,
    "Calories": 120,
    "oz": 5,
    "Origin": "Italy",
    "Rating": 0,
    "Favorites": false
  },
  {
    "Name": "Val d'Arbia",
    "Company": "Cantina Val d'Arbia",
    "Style": "Red",
    "ABV": 13,
    "Calories": 120,
    "oz": 5,
    "Origin": "Italy",
    "Rating": 0,
    "Favorites": false
  },
  {
    "Name": "Vin Santo del Chianti",
    "Company": "Cantina Chianti",
    "Style": "Dessert",
    "ABV": 15,
    "Calories": 130,
    "oz": 3,
    "Origin": "Italy",
    "Rating": 0,
    "Favorites": false
  },
  {
    "Name": "Vin Santo del Chianti Classico",
    "Company": "Cantina Chianti Classico",
    "Style": "Dessert",
    "ABV": 15,
    "Calories": 130,
    "oz": 3,
    "Origin": "Italy",
    "Rating": 0,
    "Favorites": false
  },
  {
    "Name": "Vin Santo di Montepulciano",
    "Company": "Cantina Montepulciano",
    "Style": "Dessert",
    "ABV": 15,
    "Calories": 130,
    "oz": 3,
    "Origin": "Italy",
    "Rating": 0,
    "Favorites": false
  }
]
