[
    {
        "Name": "Stella",
        "Company": "Brasseries du Maroc",
        "Style": "Pale Lager",
        "ABV": 5,
        "Calories": 148,
        "oz": 12,
        "Origin": "Morocco",
        "Ratings": [],
        "Favorites": []
    },
    {
        "Name": "Flag Sp\u00e9ciale",
        "Company": "Brasseries du Maroc",
        "Style": "Pale Lager",
        "ABV": 5,
        "Calories": 148,
        "oz": 12,
        "Origin": "Morocco",
        "Ratings": [],
        "Favorites": []
    },
    {
        "Name": "Casablanca",
        "Company": "Brasseries du Maroc",
        "Style": "Pale Lager",
        "ABV": 5,
        "Calories": 148,
        "oz": 12,
        "Origin": "Morocco",
        "Ratings": [],
        "Favorites": []
    },
    {
        "Name": "Stork",
        "Company": "Brasseries du Maroc",
        "Style": "Pale Lager",
        "ABV": 5,
        "Calories": 148,
        "oz": 12,
        "Origin": "Morocco",
        "Ratings": [],
        "Favorites": []
    },
    {
        "Name": "Dunes",
        "Company": "Brasseries du Maroc",
        "Style": "Pale Lager",
        "ABV": 5,
        "Calories": 148,
        "oz": 12,
        "Origin": "Morocco",
        "Ratings": [],
        "Favorites": []
    },
    {
        "Name": "Flag Sp\u00e9ciale Light",
        "Company": "Brasseries du Maroc",
        "Style": "Light Lager",
        "ABV": 3.5,
        "Calories": 100,
        "oz": 12,
        "Origin": "Morocco",
        "Ratings": [],
        "Favorites": []
    },
    {
        "Name": "Moussy",
        "Company": "Brasseries du Maroc",
        "Style": "Non-Alcoholic",
        "ABV": 0,
        "Calories": 10,
        "oz": 12,
        "Origin": "Morocco",
        "Ratings": [],
        "Favorites": []
    }
]