[
    {
        "Name": "Corona Extra",
        "Company": "Grupo Modelo",
        "Style": "Lager",
        "ABV": 4.6,
        "Calories": 148,
        "oz": 12,
        "Origin": "Mexico",
        "Ratings": [],
        "Favorites": []
    },
    {
        "Name": "Modelo Especial",
        "Company": "Grupo Modelo",
        "Style": "Lager",
        "ABV": 4.4,
        "Calories": 144,
        "oz": 12,
        "Origin": "Mexico",
        "Ratings": [],
        "Favorites": []
    },
    {
        "Name": "Negra Modelo",
        "Company": "Grupo Modelo",
        "Style": "Munich Dunkel Lager",
        "ABV": 5.4,
        "Calories": 173,
        "oz": 12,
        "Origin": "Mexico",
        "Ratings": [],
        "Favorites": []
    },
    {
        "Name": "Tecate",
        "Company": "Cervecer\u00eda Cuauht\u00e9moc Moctezuma (Heineken M\u00e9xico)",
        "Style": "Lager",
        "ABV": 4.5,
        "Calories": 141,
        "oz": 12,
        "Origin": "Mexico",
        "Ratings": [],
        "Favorites": []
    },
    {
        "Name": "Sol",
        "Company": "Cervecer\u00eda Cuauht\u00e9moc Moctezuma (Heineken M\u00e9xico)",
        "Style": "Lager",
        "ABV": 4.5,
        "Calories": 135,
        "oz": 12,
        "Origin": "Mexico",
        "Ratings": [],
        "Favorites": []
    },
    {
        "Name": "Carta Blanca",
        "Company": "Cervecer\u00eda Cuauht\u00e9moc Moctezuma (Heineken M\u00e9xico)",
        "Style": "Lager",
        "ABV": 4.5,
        "Calories": 139,
        "oz": 12,
        "Origin": "Mexico",
        "Ratings": [],
        "Favorites": []
    },
    {
        "Name": "Minerva Pale Ale",
        "Company": "Cervecer\u00eda Minerva",
        "Style": "Pale Ale",
        "ABV": 5.0,
        "Calories": 170,
        "oz": 12,
        "Origin": "Mexico",
        "Ratings": [],
        "Favorites": []
    },
    {
        "Name": "Minerva Stout",
        "Company": "Cervecer\u00eda Minerva",
        "Style": "Stout",
        "ABV": 6.0,
        "Calories": 180,
        "oz": 12,
        "Origin": "Mexico",
        "Ratings": [],
        "Favorites": []
    },
    {
        "Name": "Minerva Colonial",
        "Company": "Cervecer\u00eda Minerva",
        "Style": "K\u00f6lsch",
        "ABV": 4.8,
        "Calories": 160,
        "oz": 12,
        "Origin": "Mexico",
        "Ratings": [],
        "Favorites": []
    },
    {
        "Name": "Calavera Mexican Imperial Stout",
        "Company": "Cervecer\u00eda Calavera",
        "Style": "Imperial Stout",
        "ABV": 9.0,
        "Calories": 250,
        "oz": 12,
        "Origin": "Mexico",
        "Ratings": [],
        "Favorites": []
    },
    {
        "Name": "Calavera Tripel",
        "Company": "Cervecer\u00eda Calavera",
        "Style": "Tripel",
        "ABV": 9.5,
        "Calories": 220,
        "oz": 12,
        "Origin": "Mexico",
        "Ratings": [],
        "Favorites": []
    },
    {
        "Name": "Calavera Dubbel",
        "Company": "Cervecer\u00eda Calavera",
        "Style": "Dubbel",
        "ABV": 7.0,
        "Calories": 200,
        "oz": 12,
        "Origin": "Mexico",
        "Ratings": [],
        "Favorites": []
    },
    {
        "Name": "Tempus Dorada",
        "Company": "Cervecer\u00eda Primus",
        "Style": "Blonde Ale",
        "ABV": 4.3,
        "Calories": 160,
        "oz": 12,
        "Origin": "Mexico",
        "Ratings": [],
        "Favorites": []
    },
    {
        "Name": "Tempus Alt Cl\u00e1sica",
        "Company": "Cervecer\u00eda Primus",
        "Style": "Altbier",
        "ABV": 4.9,
        "Calories": 170,
        "oz": 12,
        "Origin": "Mexico",
        "Ratings": [],
        "Favorites": []
    },
    {
        "Name": "Tempus Reserva Especial",
        "Company": "Cervecer\u00eda Primus",
        "Style": "Strong Ale",
        "ABV": 7.8,
        "Calories": 210,
        "oz": 12,
        "Origin": "Mexico",
        "Ratings": [],
        "Favorites": []
    }
]